sau/__init__.py
sau/__main__.py
sau-0.1.0.dist-info/LICENSE
sau-0.1.0.dist-info/METADATA
sau-0.1.0.dist-info/WHEEL
sau-0.1.0.dist-info/top_level.txt
sau-0.1.0.dist-info/RECORD
