Metadata-Version: 2.1
Name: sau
Version: 0.1.0
Summary: The SAU Exporter is a Python-based application designed to collect and expose AWS EC2 and EBS volume metrics for monitoring and observability. It utilizes the Prometheus client library to provide an HTTP endpoint for scraping metrics.
Author-email: Emeka Ugwuanyi <ugwuanyiemy@gmail.com>
Project-URL: Homepage, https://github.com/emylincon/sau
Project-URL: Bug Tracker, https://github.com/emylincon/sau/issues
Classifier: Programming Language :: Python :: 3
Classifier: License :: OSI Approved :: MIT License
Classifier: Operating System :: OS Independent
Requires-Python: >=3.8
License-File: LICENSE
Requires-Dist: boto3 >=1.28.80
Requires-Dist: prometheus-client ==0.17.1
Requires-Dist: PyYAML >=5.3.1
Requires-Dist: requests
Requires-Dist: multiprocessing-logging ==0.3.4
